{
  "version": 1,
  "license": "CC-BY-SA-3.0",
  "copyright": "Taken from cmss13 at https://github.com/cmss13-devs/cmss13/blob/884ab172389b6fc54ef063f5fbea5e8b0a0a2235/icons/mob/mob.dmi, plasma overlay by Vermidia",
  "size": {
    "x": 32,
    "y": 32
  },
  "states": [
    {
      "name": "heal_overlay",
      "delays": [
        [
          0.2,
          0.2,
          0.2,
          0.2,
          0.2,
          0.2,
          0.2,
          0.1
        ]
      ]
    },
    {
      "name": "busy_medical",
      "delays": [
        [
          0.2,
          0.2,
          0.2,
          0.2,
          0.2,
          0.2,
          0.2,
          0.1
        ]
      ]
    },
    {
      "name": "plasma_overlay",
      "delays": [
        [
          0.2,
          0.2,
          0.2,
          0.2,
          0.2,
          0.2,
          0.2,
          0.1
        ]
      ]
    }
  ]
}